ascii_table/Align.py
ascii_table/Cell.py
ascii_table/Column.py
ascii_table/Table.py
ascii_table/__init__.py
ascii_table-0.1.0.dist-info/METADATA
ascii_table-0.1.0.dist-info/RECORD
ascii_table-0.1.0.dist-info/WHEEL
ascii_table-0.1.0.dist-info/top_level.txt
