Metadata-Version: 2.1
Name: ascii-table
Version: 0.1.0
Summary: An simple json to ascii table Python package.
Home-page: https://github.com/johnyob/ascii-table
Author: Alistair O'Brien
Author-email: alistair.o'brien@ellesmere.com
License: UNKNOWN
Platform: UNKNOWN
